credit_card_validator/__init__.py
credit_card_validator/card_validator.py
credit_card_validator/exceptions.py
credit_card_validator/schemas.py
credit_card_validator/version.py
credit_card_validator-1.1.1.dist-info/LICENSE
credit_card_validator-1.1.1.dist-info/METADATA
credit_card_validator-1.1.1.dist-info/WHEEL
credit_card_validator-1.1.1.dist-info/top_level.txt
credit_card_validator-1.1.1.dist-info/RECORD
